fantasy_ga/__init__.py
fantasy_ga/__main__.py
fantasy_ga/configs.py
fantasy_ga/lineup_generator.py
fantasy_ga-0.4.3.dist-info/LICENSE
fantasy_ga-0.4.3.dist-info/METADATA
fantasy_ga-0.4.3.dist-info/WHEEL
fantasy_ga-0.4.3.dist-info/entry_points.txt
fantasy_ga-0.4.3.dist-info/top_level.txt
fantasy_ga-0.4.3.dist-info/RECORD
