Metadata-Version: 2.1
Name: fantasy-ga
Version: 0.4.3
Summary: Genetic algorithm library to generate fantasy sports lineups
Author-email: Kengo Arao <kengo@hey.com>
License: 
Project-URL: Homepage, https://github.com/KengoA/fantasy-ga
Keywords: genetic-algorithm,fantasy-sports,fantasy-basketball,fantasy-football,fantasy-baseball,fantasy-hockey
Classifier: License :: OSI Approved :: MIT License
Classifier: Programming Language :: Python :: 3
Requires-Python: >=3.9
License-File: LICENSE
Requires-Dist: numpy ==1.24.2
Provides-Extra: dev
Requires-Dist: black ; extra == 'dev'
Requires-Dist: pip-tools ; extra == 'dev'
Requires-Dist: pytest ; extra == 'dev'
Requires-Dist: pydantic ; extra == 'dev'
